docs/source/conf.py
examples/competitions_in_summer_2024.py
examples/events_count.py
judobase/__init__.py
judobase/base.py
judobase/judobase_api.py
judobase/schemas.py
judobase/version.py
judobase-1.0.2.dist-info/licenses/LICENSE
tests/conftest.py
tests/test_base.py
tests/test_judobase_api.py
judobase-1.0.2.dist-info/METADATA
judobase-1.0.2.dist-info/WHEEL
judobase-1.0.2.dist-info/top_level.txt
judobase-1.0.2.dist-info/RECORD
