Metadata-Version: 2.4
Name: judobase
Version: 1.0.2
Summary: Python Judobase API async client
Author-email: ddzgoev <ddzgoev@gmail.com>
License: MIT
Project-URL: Homepage, https://github.com/DavidDzgoev/judobase
Project-URL: Documentation, https://daviddzgoev.github.io/judobase/
Project-URL: Repository, https://github.com/DavidDzgoev/judobase
Keywords: judobase,wrapper,client,async,api
Classifier: Programming Language :: Python :: 3
Classifier: Programming Language :: Python :: 3.11
Classifier: License :: OSI Approved :: MIT License
Classifier: Operating System :: OS Independent
Classifier: Framework :: aiohttp
Classifier: Framework :: Pydantic :: 2
Requires-Python: >=3.9
License-File: LICENSE
Requires-Dist: aioresponses>=0.7.7
Requires-Dist: aiohttp>=3.11.11
Requires-Dist: pydantic>=2.10.5
Requires-Dist: setuptools>=75.6.0
Provides-Extra: tests
Requires-Dist: pytest>=8.3.4; extra == "tests"
Dynamic: license-file
